freeze/__init__.py
freeze/__main__.py
freeze/_argparse.py
freeze/_base.py
freeze/_getopt.py
freeze_too-0.0.1.dist-info/METADATA
freeze_too-0.0.1.dist-info/WHEEL
freeze_too-0.0.1.dist-info/entry_points.txt
freeze_too-0.0.1.dist-info/top_level.txt
freeze_too-0.0.1.dist-info/RECORD
