Metadata-Version: 2.1
Name: freeze-too
Version: 0.0.1
Home-page: 
Classifier: Programming Language :: Python :: 3
Classifier: Operating System :: OS Independent
